extend_orfs_pyranges
