Metadata-Version: 2.1
Name: extend-orfs-pyranges
Version: 0.1.4
Summary: Fork of Joan Pallares extend_orf based on pyranges
Home-page: https://github.com/pypa/sampleproject
Author: Marco Mariotti and Joan Pallares
Author-email: marco.mariotti@ub.edu
Classifier: Programming Language :: Python :: 3
Classifier: License :: OSI Approved :: MIT License
Classifier: Operating System :: OS Independent
Requires-Python: >=3.6
